pkg/__init__.py
pkg/hi.py
dearpyguipip-0.0.2.dist-info/LICENSE.txt
dearpyguipip-0.0.2.dist-info/METADATA
dearpyguipip-0.0.2.dist-info/WHEEL
dearpyguipip-0.0.2.dist-info/top_level.txt
dearpyguipip-0.0.2.dist-info/RECORD
