Metadata-Version: 2.1
Name: dearpyguipip
Version: 0.0.2
Summary: poc placeholder package
Author: cody zacharias
Author-email: codyzacharias@gmail.com
Maintainer: cody zacharias
Maintainer-email: codyzacharias@gmail.com
License: MIT License
Project-URL: Homepage, https://hackerone.com/codyzacharias
Keywords: package,setuptools
Classifier: License :: OSI Approved :: MIT License
Classifier: Programming Language :: Python
Requires-Python: >=3.7
License-File: LICENSE.txt
Requires-Dist: requests
Provides-Extra: dev
Requires-Dist: pytest ==5.0.0 ; extra == 'dev'
Requires-Dist: pytest-cov[all] ; extra == 'dev'
Requires-Dist: mypy ==0.910 ; extra == 'dev'
Requires-Dist: black ==21.10b0 ; extra == 'dev'
